lang2shell/__init__.py
lang2shell/main.py
lang2shell-0.1.4.dist-info/METADATA
lang2shell-0.1.4.dist-info/WHEEL
lang2shell-0.1.4.dist-info/entry_points.txt
lang2shell-0.1.4.dist-info/RECORD
