Metadata-Version: 2.1
Name: lang2shell
Version: 0.1.4
Summary: A Python package to execute natural language commands as Linux shell commands using OpenAI.
License: MIT
Author: Your Name
Author-email: your.email@example.com
Requires-Python: >=3.8,<4.0
Classifier: License :: OSI Approved :: MIT License
Classifier: Programming Language :: Python :: 3
Classifier: Programming Language :: Python :: 3.8
Classifier: Programming Language :: Python :: 3.9
Classifier: Programming Language :: Python :: 3.10
Classifier: Programming Language :: Python :: 3.11
Classifier: Programming Language :: Python :: 3.12
Classifier: Programming Language :: Python :: 3.13
Requires-Dist: openai (>=1.57.2,<2.0.0)
